dappier_mcp/__init__.py
dappier_mcp/server.py
dappier_mcp-0.3.2.dist-info/METADATA
dappier_mcp-0.3.2.dist-info/WHEEL
dappier_mcp-0.3.2.dist-info/entry_points.txt
dappier_mcp-0.3.2.dist-info/licenses/LICENSE
dappier_mcp-0.3.2.dist-info/RECORD
